sinkaf/__init__.py
sinkaf/sinkaf.py
sinkaf/utils.py
sinkaf-1.0.0.dist-info/LICENSE
sinkaf-1.0.0.dist-info/METADATA
sinkaf-1.0.0.dist-info/WHEEL
sinkaf-1.0.0.dist-info/top_level.txt
sinkaf-1.0.0.dist-info/RECORD
