Metadata-Version: 2.1
Name: sinkaf
Version: 1.0.0
Summary: Türkçe küfürlü içerikleri bulan bir kütüphane
Home-page: https://github.com/eonurk/sinkaf
Author: E Onur Karakaslar
Author-email: eonurkara@gmail.com
License: UNKNOWN
Platform: UNKNOWN
Classifier: Programming Language :: Python :: 3
Classifier: License :: OSI Approved :: MIT License
Classifier: Operating System :: OS Independent
Requires-Python: >=3.6
